{
    "receiver": "dogalarm",
    "status": "firing",
    "alerts": [
      {
        "status": "firing",
        "labels": {
          "alertname": "HTTP QPS",
          "app": "ordersvc",
          "dogapm": "1",
          "grafana_folder": "dogapm"
        },
        "annotations": {},
        "startsAt": "2024-10-23T03:10:10Z",
        "endsAt": "0001-01-01T00:00:00Z",
        "generatorURL": "http://localhost:3000/alerting/grafana/be1p7e2ma14owe/view?orgId=1",
        "fingerprint": "348b8dcb525a5955",
        "silenceURL": "http://localhost:3000/alerting/silence/new?alertmanager=grafana&matcher=alertname%3DHTTP+QPS&matcher=app%3Dordersvc&matcher=dogapm%3D1&matcher=grafana_folder%3Ddogapm&orgId=1",
        "dashboardURL": "http://localhost:3000/d/ce0xz85uxmigwf?orgId=1",
        "panelURL": "http://localhost:3000/d/ce0xz85uxmigwf?orgId=1&viewPanel=2",
        "values": {
          "B": 0.1428920058349484,
          "C": 1
        },
        "valueString": "[ var='B' labels={app=ordersvc} value=0.1428920058349484 ], [ var='C' labels={app=ordersvc} value=1 ]"
      },
      {
        "status": "firing",
        "labels": {
          "alertname": "HTTP QPS",
          "app": "skusvc",
          "dogapm": "1",
          "grafana_folder": "dogapm"
        },
        "annotations": {},
        "startsAt": "2024-10-23T03:10:10Z",
        "endsAt": "0001-01-01T00:00:00Z",
        "generatorURL": "http://localhost:3000/alerting/grafana/be1p7e2ma14owe/view?orgId=1",
        "fingerprint": "834c850ea41298a2",
        "silenceURL": "http://localhost:3000/alerting/silence/new?alertmanager=grafana&matcher=alertname%3DHTTP+QPS&matcher=app%3Dskusvc&matcher=dogapm%3D1&matcher=grafana_folder%3Ddogapm&orgId=1",
        "dashboardURL": "http://localhost:3000/d/ce0xz85uxmigwf?orgId=1",
        "panelURL": "http://localhost:3000/d/ce0xz85uxmigwf?orgId=1&viewPanel=2",
        "values": {
          "B": 0.14002800826670703,
          "C": 1
        },
        "valueString": "[ var='B' labels={app=skusvc} value=0.14002800826670703 ], [ var='C' labels={app=skusvc} value=1 ]"
      },
      {
        "status": "firing",
        "labels": {
          "alertname": "HTTP QPS",
          "app": "usrsvc",
          "dogapm": "1",
          "grafana_folder": "dogapm"
        },
        "annotations": {},
        "startsAt": "2024-10-23T03:10:10Z",
        "endsAt": "0001-01-01T00:00:00Z",
        "generatorURL": "http://localhost:3000/alerting/grafana/be1p7e2ma14owe/view?orgId=1",
        "fingerprint": "b6ea381fa6651507",
        "silenceURL": "http://localhost:3000/alerting/silence/new?alertmanager=grafana&matcher=alertname%3DHTTP+QPS&matcher=app%3Dusrsvc&matcher=dogapm%3D1&matcher=grafana_folder%3Ddogapm&orgId=1",
        "dashboardURL": "http://localhost:3000/d/ce0xz85uxmigwf?orgId=1",
        "panelURL": "http://localhost:3000/d/ce0xz85uxmigwf?orgId=1&viewPanel=2",
        "values": {
          "B": 0.14246865902864417,
          "C": 1
        },
        "valueString": "[ var='B' labels={app=usrsvc} value=0.14246865902864417 ], [ var='C' labels={app=usrsvc} value=1 ]"
      }
    ],
    "groupLabels": {
      "alertname": "HTTP QPS",
      "grafana_folder": "dogapm"
    },
    "commonLabels": {
      "alertname": "HTTP QPS",
      "dogapm": "1",
      "grafana_folder": "dogapm"
    },
    "commonAnnotations": {},
    "externalURL": "http://localhost:3000/",
    "version": "1",
    "groupKey": "{}/{__grafana_autogenerated__=\"true\"}/{__grafana_receiver__=\"dogalarm\"}:{alertname=\"HTTP QPS\", grafana_folder=\"dogapm\"}",
    "truncatedAlerts": 0,
    "orgId": 1,
    "title": "[FIRING:3] HTTP QPS dogapm (1)",
    "state": "alerting",
    "message": "**Firing**\n\nValue: B=0.1428920058349484, C=1\nLabels:\n - alertname = HTTP QPS\n - app = ordersvc\n - dogapm = 1\n - grafana_folder = dogapm\nAnnotations:\nSource: http://localhost:3000/alerting/grafana/be1p7e2ma14owe/view?orgId=1\nSilence: http://localhost:3000/alerting/silence/new?alertmanager=grafana&matcher=alertname%3DHTTP+QPS&matcher=app%3Dordersvc&matcher=dogapm%3D1&matcher=grafana_folder%3Ddogapm&orgId=1\nDashboard: http://localhost:3000/d/ce0xz85uxmigwf?orgId=1\nPanel: http://localhost:3000/d/ce0xz85uxmigwf?orgId=1&viewPanel=2\n\nValue: B=0.14002800826670703, C=1\nLabels:\n - alertname = HTTP QPS\n - app = skusvc\n - dogapm = 1\n - grafana_folder = dogapm\nAnnotations:\nSource: http://localhost:3000/alerting/grafana/be1p7e2ma14owe/view?orgId=1\nSilence: http://localhost:3000/alerting/silence/new?alertmanager=grafana&matcher=alertname%3DHTTP+QPS&matcher=app%3Dskusvc&matcher=dogapm%3D1&matcher=grafana_folder%3Ddogapm&orgId=1\nDashboard: http://localhost:3000/d/ce0xz85uxmigwf?orgId=1\nPanel: http://localhost:3000/d/ce0xz85uxmigwf?orgId=1&viewPanel=2\n\nValue: B=0.14246865902864417, C=1\nLabels:\n - alertname = HTTP QPS\n - app = usrsvc\n - dogapm = 1\n - grafana_folder = dogapm\nAnnotations:\nSource: http://localhost:3000/alerting/grafana/be1p7e2ma14owe/view?orgId=1\nSilence: http://localhost:3000/alerting/silence/new?alertmanager=grafana&matcher=alertname%3DHTTP+QPS&matcher=app%3Dusrsvc&matcher=dogapm%3D1&matcher=grafana_folder%3Ddogapm&orgId=1\nDashboard: http://localhost:3000/d/ce0xz85uxmigwf?orgId=1\nPanel: http://localhost:3000/d/ce0xz85uxmigwf?orgId=1&viewPanel=2\n"
  }